[
  {
    "id": "ach_first_blood",
    "name": "初出茅庐",
    "description": "完成第一次战斗",
    "category": "combat",
    "condition": { "type": "battle_count", "value": 1 },
    "rewards": { "exp": 50, "title": "初出茅庐" }
  },
  {
    "id": "ach_warrior_10",
    "name": "百战之师",
    "description": "完成10次战斗",
    "category": "combat",
    "condition": { "type": "battle_count", "value": 10 },
    "rewards": { "exp": 200, "gold": 100 }
  },
  {
    "id": "ach_warrior_50",
    "name": "身经百战",
    "description": "完成50次战斗",
    "category": "combat",
    "condition": { "type": "battle_count", "value": 50 },
    "rewards": { "exp": 500, "gold": 500 }
  },
  {
    "id": "ach_level_10",
    "name": "小有所成",
    "description": "达到10级",
    "category": "level",
    "condition": { "type": "level", "value": 10 },
    "rewards": { "exp": 200, "gold": 200 }
  },
  {
    "id": "ach_level_30",
    "name": "江湖新秀",
    "description": "达到30级",
    "category": "level",
    "condition": { "type": "level", "value": 30 },
    "rewards": { "exp": 1000, "gold": 1000 }
  },
  {
    "id": "ach_level_50",
    "name": "一代宗师",
    "description": "达到50级",
    "category": "level",
    "condition": { "type": "level", "value": 50 },
    "rewards": { "exp": 5000, "gold": 5000, "title": "一代宗师" }
  },
  {
    "id": "ach_rich_1000",
    "name": "小有积蓄",
    "description": "累计获得1000金币",
    "category": "wealth",
    "condition": { "type": "gold_earned", "value": 1000 },
    "rewards": { "exp": 100 }
  },
  {
    "id": "ach_rich_10000",
    "name": "富甲一方",
    "description": "累计获得10000金币",
    "category": "wealth",
    "condition": { "type": "gold_earned", "value": 10000 },
    "rewards": { "exp": 500, "title": "富甲一方" }
  },
  {
    "id": "ach_explorer_10",
    "name": "行脚商人",
    "description": "探索10个不同房间",
    "category": "exploration",
    "condition": { "type": "rooms_visited", "value": 10 },
    "rewards": { "exp": 200 }
  },
  {
    "id": "ach_explorer_30",
    "name": "踏遍江湖",
    "description": "探索30个不同房间",
    "category": "exploration",
    "condition": { "type": "rooms_visited", "value": 30 },
    "rewards": { "exp": 500, "title": "踏遍江湖" }
  },
  {
    "id": "ach_quest_5",
    "name": "任务达人",
    "description": "完成5个任务",
    "category": "quest",
    "condition": { "type": "quests_completed", "value": 5 },
    "rewards": { "exp": 300 }
  },
  {
    "id": "ach_quest_20",
    "name": "使命必达",
    "description": "完成20个任务",
    "category": "quest",
    "condition": { "type": "quests_completed", "value": 20 },
    "rewards": { "exp": 1000, "title": "使命必达" }
  },
  {
    "id": "ach_faction_join",
    "name": "拜入师门",
    "description": "加入一个门派",
    "category": "faction",
    "condition": { "type": "faction_joined" },
    "rewards": { "exp": 100 }
  },
  {
    "id": "ach_faction_elder",
    "name": "门派栋梁",
    "description": "门派等级达到长老",
    "category": "faction",
    "condition": { "type": "faction_rank", "value": "elder" },
    "rewards": { "exp": 2000, "title": "门派栋梁" }
  },
  {
    "id": "ach_pvp_first",
    "name": "初试锋芒",
    "description": "完成第一次PVP战斗",
    "category": "pvp",
    "condition": { "type": "pvp_count", "value": 1 },
    "rewards": { "exp": 200 }
  },
  {
    "id": "ach_pvp_10",
    "name": "竞技高手",
    "description": "完成10次PVP战斗",
    "category": "pvp",
    "condition": { "type": "pvp_count", "value": 10 },
    "rewards": { "exp": 1000, "title": "竞技高手" }
  },
  {
    "id": "ach_death_1",
    "name": "劫后余生",
    "description": "第一次死亡后复活",
    "category": "special",
    "condition": { "type": "deaths", "value": 1 },
    "rewards": { "exp": 50 }
  },
  {
    "id": "ach_trade_1",
    "name": "互通有无",
    "description": "完成第一次玩家交易",
    "category": "social",
    "condition": { "type": "trades_completed", "value": 1 },
    "rewards": { "exp": 100 }
  },
  {
    "id": "ach_dungeon_1",
    "name": "初探秘境",
    "description": "完成第一次副本",
    "category": "combat",
    "condition": { "type": "dungeons_completed", "value": 1 },
    "rewards": { "exp": 200, "title": "秘境行者" }
  },
  {
    "id": "ach_dungeon_10",
    "name": "秘境常客",
    "description": "完成10次副本",
    "category": "combat",
    "condition": { "type": "dungeons_completed", "value": 10 },
    "rewards": { "exp": 1000, "gold": 500 }
  },
  {
    "id": "ach_craft_5",
    "name": "能工巧匠",
    "description": "制造5次物品（锻造/炼药/烹饪）",
    "category": "crafting",
    "condition": { "type": "crafting_count", "value": 5 },
    "rewards": { "exp": 300 }
  },
  {
    "id": "ach_craft_25",
    "name": "天工开物",
    "description": "制造25次物品",
    "category": "crafting",
    "condition": { "type": "crafting_count", "value": 25 },
    "rewards": { "exp": 1000, "title": "天工开物" }
  },
  {
    "id": "ach_checkin_3",
    "name": "三日之约",
    "description": "连续签到3天",
    "category": "daily",
    "condition": { "type": "checkin_streak", "value": 3 },
    "rewards": { "exp": 100, "gold": 50 }
  },
  {
    "id": "ach_checkin_7",
    "name": "七日之约",
    "description": "连续签到7天",
    "category": "daily",
    "condition": { "type": "checkin_streak", "value": 7 },
    "rewards": { "exp": 500, "gold": 200, "title": "七日之约" }
  },
  {
    "id": "ach_gang_create",
    "name": "开宗立派",
    "description": "创建一个帮派",
    "category": "social",
    "condition": { "type": "gang_joined" },
    "rewards": { "exp": 300, "title": "一帮之主" }
  },
  {
    "id": "ach_level_80",
    "name": "江湖至尊",
    "description": "达到80级",
    "category": "level",
    "condition": { "type": "level", "value": 80 },
    "rewards": { "exp": 10000, "gold": 10000, "title": "江湖至尊" }
  },
  {
    "id": "ach_rich_50000",
    "name": "富可敌国",
    "description": "累计获得50000金币",
    "category": "wealth",
    "condition": { "type": "gold_earned", "value": 50000 },
    "rewards": { "exp": 2000, "title": "富可敌国" }
  },
  {
    "id": "ach_explorer_all",
    "name": "踏遍山河",
    "description": "探索50个不同房间",
    "category": "exploration",
    "condition": { "type": "rooms_visited", "value": 50 },
    "rewards": { "exp": 2000, "title": "踏遍山河" }
  }
]
